nextpc.v
`timescale 1ns / 1ps

module NextPCLogic(NextPC, CurrentPC, SignExtImm64, Branch, ALUZero, Uncondbranch);

	//inputs outputs
	output reg [63:0] NextPC;
	input [63:0] CurrentPC;
	input [63:0] SignExtImm64;
	input Branch, ALUZero,Uncondbranch;

	//behavioral model of PC logic
	always @(*)
	begin
		if (Uncondbranch || (Branch && ALUZero)) // pc takes branch or unconditional branch
			#3 NextPC = (SignExtImm64 << 2 ) + CurrentPC;
		else // else pc goes to next pc counter
			#2 NextPC = CurrentPC + 4;
			
	end
	
	 

endmodule

DataMemory.v
`timescale 1ns / 1ps

`define SIZE 1024

module DataMemory(ReadData , Address , WriteData , MemoryRead , MemoryWrite , Clock);
    input [63:0]      WriteData;
    input [63:0]      Address;
    input             Clock, MemoryRead, MemoryWrite;
    output reg [63:0] ReadData;

    reg [7:0]         memBank [`SIZE-1:0];


    // This task is used to write arbitrary data to the Data Memory by
    // the intialization block.
    task initset;
      input [63:0] addr;
      input [63:0] data;
      begin
     memBank[addr] =  data[63:56] ; // Big-endian for the win...
     memBank[addr+1] =  data[55:48];
     memBank[addr+2] =  data[47:40];
     memBank[addr+3] =  data[39:32];
     memBank[addr+4] =  data[31:24];
     memBank[addr+5] =  data[23:16];
     memBank[addr+6] =  data[15:8];
     memBank[addr+7] =  data[7:0];
      end
    endtask


    initial
    begin
        // preseting some data in the data memory used by test #1

        // Address 0x0 gets 0x1
        initset( 64'h0,  64'h1);  //Counter variable
        initset( 64'h8,  64'ha);  //Part of mask
        initset( 64'h10, 64'h5);  //Other part of mask
        initset( 64'h18, 64'h0ffbea7deadbeeff); //big constant
        initset( 64'h20, 64'h0); //clearing space

        // Add any data you need for your tests here.

    end

    // This always block reads the data memory and places a double word
    // on the ReadData bus.
    always @(posedge Clock)
    begin
        if(MemoryRead)
        begin
            ReadData[63:56] <= #20 memBank[Address];
            ReadData[55:48] <= #20 memBank[Address+1];
            ReadData[47:40] <= #20 memBank[Address+2];
            ReadData[39:32] <= #20 memBank[Address+3];
            ReadData[31:24] <= #20 memBank[Address+4];
            ReadData[23:16] <= #20 memBank[Address+5];
            ReadData[15:8] <= #20 memBank[Address+6];
            ReadData[7:0] <= #20 memBank[Address+7];
        end
    end

    // This always block takes data from the WriteData bus and writes
    // it into the DataMemory.
    always @(posedge Clock)
    begin
        if(MemoryWrite)
        begin
            memBank[Address] <= #20 WriteData[63:56] ;
            memBank[Address+1] <= #20 WriteData[55:48];
            memBank[Address+2] <= #20 WriteData[47:40];
            memBank[Address+3] <= #20 WriteData[39:32];
            memBank[Address+4] <= #20 WriteData[31:24];
            memBank[Address+5] <= #20 WriteData[23:16];
            memBank[Address+6] <= #20 WriteData[15:8];
            memBank[Address+7] <= #20 WriteData[7:0];
            // Could be useful for debugging:
            // $display("Writing Address:%h Data:%h",Address, WriteData);
        end
    end
endmodule

ALU.v
`timescale 1ns / 1ps

`define AND   4'b0000
`define OR    4'b0001
`define ADD   4'b0010
`define SUB   4'b0110
`define PassB 4'b0111


module ALU(BusW, BusA, BusB, ALUCtrl, Zero);
    
    parameter n = 64;
	 
     //input and output ports
    output  [n-1:0] BusW;
    input   [n-1:0] BusA, BusB;
    input   [3:0] ALUCtrl;
    output  Zero;
    
    reg     [n-1:0] BusW;
    
    always @(ALUCtrl or BusA or BusB) begin
        case(ALUCtrl)
            `AND: BusW <= #20 (BusA & BusB);
            `OR: BusW <= #20 (BusA | BusB);
            `ADD: BusW <= #20 (BusA + BusB);
            `SUB: BusW <= #20 (BusA - BusB);
            `PassB: BusW <= #20 BusB;
        endcase
    end

    assign #1 Zero = (BusW) ? 1'b0 : 1'b1; // 1 when BusW is 0, and 0 otherwise.
endmodule

SignExtender.v
`timescale 1ns / 1ps

module SignExtender(Imm64, Imm26, Ctrl); 
 
  /*input and output ports*/
  output [63:0] Imm64; 
  input [25:0] Imm26; 
  input [2:0] Ctrl; 

  reg [63:0] Imm64Reg;

  always@ (*) begin

    if(Ctrl == 3'b000)begin //I-type sign extender for add and sub
      Imm64Reg = {{52{Imm26[1'b0]}} , Imm26[21:10]};
    end
    else if(Ctrl == 3'b001)begin //D-type sign extender for load and store
      Imm64Reg = {{55{Imm26[20]}} , Imm26[20:12]};
    end
    else if(Ctrl == 3'b010)begin //B-type sign extender for branch
      Imm64Reg = {{38{Imm26[25]}} , Imm26};
    end   
    else if(Ctrl == 3'b011) begin //CB-type sign extender for conditional branch
      Imm64Reg = {{45{Imm26[23]}} , Imm26[23:5]};
    end
    else begin //IM-type sign extender for MOVZ
      Imm64Reg = { 48'b0, {Imm26[20:5]} };
      if(Imm26[22:21] != 2'b00) begin
      	Imm64Reg =  Imm64Reg << ((Imm26[22:21]) *16);
      end
    end
                  
  end

  assign Imm64 = Imm64Reg;

endmodule

RegisterFile.v
`timescale 1ns / 1ps

module RegisterFile(BusA, BusB, BusW, RA, RB, RW, RegWr, Clk); 

    //64 bit register file inputs and outputs
    output [63:0] BusA;
    output [63:0] BusB;
    input [63:0] BusW;
    input [4:0] RA;
    input [4:0] RB;
    input [4:0] RW;
    input RegWr;
    input Clk;
    reg [63:0] registers [31:0];
    

    //behavioral model of register file
    always @ (negedge Clk) begin
        if(RegWr) //When RegWr is set to 1, then the data on Bus W is stored in the register specified by Rw with dealy of 3
            registers[RW] <= #3 BusW;
    end

    //Data from registers Ra and Rb is sent on Bus A and Bus B respectively, after a delay of 2 tics.  Also sets Register 31 equal to zero
    assign #2 BusA = (RA == 31) ? 0 : registers[RA];
    assign #2 BusB = (RB == 31  ) ? 0: registers[RB];

    
endmodule

Control.v
`timescale 1ns / 1ps

`define OPCODE_ANDREG 11'b?0001010???
`define OPCODE_ORRREG 11'b?0101010???
`define OPCODE_ADDREG 11'b?0?01011???
`define OPCODE_SUBREG 11'b?1?01011???

`define OPCODE_ADDIMM 11'b?0?10001???
`define OPCODE_SUBIMM 11'b?1?10001???

`define OPCODE_MOVZ   11'b110100101??

`define OPCODE_B      11'b?00101?????
`define OPCODE_CBZ    11'b?011010????

`define OPCODE_LDUR   11'b??111000010
`define OPCODE_STUR   11'b??111000000

module control(
    output reg reg2loc,
    output reg alusrc,
    output reg mem2reg,
    output reg regwrite,
    output reg memread,
    output reg memwrite,
    output reg branch,
    output reg uncond_branch,
    output reg [3:0] aluop,
    output reg [2:0] signop,
    input [10:0] opcode
);

always @(*)
begin
    casez (opcode)
    
      `OPCODE_ANDREG: //AND Registers
        begin
            reg2loc       <= 1'b0;
            alusrc        <= 1'b0;
            mem2reg       <= 1'b0;
            regwrite      <= 1'b1;
            memread       <= 1'b0;
            memwrite      <= 1'b0;
            branch        <= 1'b0;
            uncond_branch <= 1'b0;
            aluop         <= 4'b0000;
            signop        <= 3'bxxx;
        end
      
      `OPCODE_ORRREG: //OR Registers
        begin
            reg2loc       <= 1'b0;
            alusrc        <= 1'b0;
            mem2reg       <= 1'b0;
            regwrite      <= 1'b1;
            memread       <= 1'b0;
            memwrite      <= 1'b0;
            branch        <= 1'b0;
            uncond_branch <= 1'b0;
            aluop         <= 4'b0001;
            signop        <= 3'bxxx;
        end
      
      `OPCODE_ADDREG://ADD Registers
        begin
            reg2loc       <= 1'b0;
            alusrc        <= 1'b0;
            mem2reg       <= 1'b0;
            regwrite      <= 1'b1;
            memread       <= 1'b0;
            memwrite      <= 1'b0;
            branch        <= 1'b0;
            uncond_branch <= 1'b0;
            aluop         <= 4'b0010;
            signop        <= 3'bxxx;
        end
      
      `OPCODE_SUBREG: //SUBTRACT Registers
        begin
            reg2loc       <= 1'b0;
            alusrc        <= 1'b0;
            mem2reg       <= 1'b0;
            regwrite      <= 1'b1;
            memread       <= 1'b0;
            memwrite      <= 1'b0;
            branch        <= 1'b0;
            uncond_branch <= 1'b0;
            aluop         <= 4'b0110;
            signop        <= 3'bxxx;
        end
      
      `OPCODE_ADDIMM: //ADD Immediate
        begin
            reg2loc       <= 1'b0;
            alusrc        <= 1'b1;
            mem2reg       <= 1'b0;
            regwrite      <= 1'b1;
            memread       <= 1'b0;
            memwrite      <= 1'b0;
            branch        <= 1'b0;
            uncond_branch <= 1'b0;
            aluop         <= 4'b0010;
            signop        <= 3'b000;
        end
      
      `OPCODE_SUBIMM://SUBTRACT Immediate
        begin
            reg2loc       <= 1'b0;
            alusrc        <= 1'b1;
            mem2reg       <= 1'b0;
            regwrite      <= 1'b1;
            memread       <= 1'b0;
            memwrite      <= 1'b0;
            branch        <= 1'b0;
            uncond_branch <= 1'b0;
            aluop         <= 4'b0110;
            signop        <= 3'b000;
        end

      `OPCODE_LDUR: //LDUR
        begin
            reg2loc       <= 1'bx;
            alusrc        <= 1'b1;
            mem2reg       <= 1'b1;
            regwrite      <= 1'b1;
            memread       <= 1'b1;
            memwrite      <= 1'b0;
            branch        <= 1'b0;
            uncond_branch <= 1'b0;
            aluop         <= 4'b0010;
            signop        <= 3'b001;
        end
      
      `OPCODE_STUR: //STUR
        begin
            reg2loc       <= 1'b1;
            alusrc        <= 1'b1;
            mem2reg       <= 1'bx;
            regwrite      <= 1'b0;
            memread       <= 1'b0;
            memwrite      <= 1'b1;
            branch        <= 1'b0;
            uncond_branch <= 1'b0;
            aluop         <= 4'b0010;
            signop        <= 3'b001;
        end
      
      `OPCODE_CBZ: //CBZ
        begin
            reg2loc       <= 1'b1;
            alusrc        <= 1'b0;
            mem2reg       <= 1'bx;
            regwrite      <= 1'b0;
            memread       <= 1'b0;
            memwrite      <= 1'b0;
            branch        <= 1'b1;
            uncond_branch <= 1'bx;
            aluop         <= 4'b0111;
            signop        <= 3'b011;
        end
      
      `OPCODE_B: //B
        begin
            reg2loc       <= 1'b1;
            alusrc        <= 1'bx;
            mem2reg       <= 1'bx;
            regwrite      <= 1'b0;
            memread       <= 1'b0;
            memwrite      <= 1'b0;
            branch        <= 1'bx;
            uncond_branch <= 1'b1;
            aluop         <= 4'bxxxx;
            signop        <= 3'b010;
        end

        `OPCODE_MOVZ: //MOVZ 
        begin
            reg2loc       <= 1'bx;
            alusrc        <= 1'b1; //ALU BusB input will be the SignExtender
            mem2reg       <= 1'b0;
            regwrite      <= 1'b1;
            memread       <= 1'b0;
            memwrite      <= 1'b0;
            branch        <= 1'b0;
            uncond_branch <= 1'b0;
            aluop         <= 4'b0111; //pass input b (BusB) (b would be the SignExtender)
            signop        <= 3'b1xx;
        end

      default:
        begin
            reg2loc       <= 1'bx;
            alusrc        <= 1'bx;
            mem2reg       <= 1'bx;
            regwrite      <= 1'b0;
            memread       <= 1'b0;
            memwrite      <= 1'b0;
            branch        <= 1'b0;
            uncond_branch <= 1'b0;
            aluop         <= 4'bxxxx;
            signop        <= 3'bxxx;
        end
    endcase
end

endmodule

InstructionMemory-1.v
`timescale 1ns / 1ps
/*
 * Module: InstructionMemory
 *
 * Implements read-only instruction memory
 *
 */
module InstructionMemory(Data, Address);
    output [31:0] Data;
    input [63:0]  Address;
    reg [31:0] 	 Data;

    always @ (Address) begin
        case(Address)
        /* Test Program 1:
         * Program loads constants from the data memory. Uses these constants to test
         * the following instructions: LDUR, ORR, AND, CBZ, ADD, SUB, STUR and B.
         *
         * Assembly code for test:
         *
         * 0x00: ORR  X20, XZR, XZR     //Create a base memory address
         * 0x04: LDUR X9,  [X20, 0x0]   //Load 1 into x9
         * 0x08: LDUR X10, [X20, 0x8]   //Load a into x10
         * 0x0c: LDUR X11, [X20, 0x10]  //Load 5 into x11
         * 0x10: LDUR X12, [X20, 0x18]  //Load big constant into x12
         * 0x14: LDUR X13, [X20, 0x20]  //load a 0 into X13
         *
         * 0x18: ORR X10, X10, X11  //Create mask of 0xf
         * 0x1c: AND X12, X12, X10  //Mask off low order bits of big constant/
         *
         * loop:
         * 0x20: CBZ X12, end  //while X12 is not 0
         * 0x24: ADD X13, X13, X9  //Increment counter in X13
         * 0x28: SUB X12, X12, X9  //Decrement remainder of big constant in X12
         * 0x2c: B loop  //Repeat till X12 is 0
         * 0x30: STUR X13, [X20, 0x20]  //store back the counter value into the memory location 0x20
         * 0x34: LDUR X13, [X20, 0x20]  //One last load to place stored value on memdbus for test checking.
         */

        64'h000: Data = 32'hAA1F03F4;
        64'h004: Data = 32'hF8400289;
        64'h008: Data = 32'hF840828A;
        64'h00c: Data = 32'hF841028B;
        64'h010: Data = 32'hF841828C;
        64'h014: Data = 32'hF842028D;
        64'h018: Data = 32'hAA0B014A;
        64'h01c: Data = 32'h8A0A018C;
        64'h020: Data = 32'hB400008C;
        64'h024: Data = 32'h8B0901AD;
        64'h028: Data = 32'hCB09018C;
        64'h02c: Data = 32'h17FFFFFD;
        64'h030: Data = 32'hF802028D;
        64'h034: Data = 32'hF842028D;


        /* Add code for your tests here */
		/* Test Program 2:
         * Assembly code for test:
         *
         * 0x38: MOVZ X14, 0x1234, 0x48  //wirte 1234 LSL 48 into x14
         * 0x3c: MOVZ X15, 0x5678, 0x32  //wirte 5678 LSL 32 into x15
         * 0x40: MOVZ X16, 0x9abc, 0x16  //wirte 1234 LSL 16 into x16
         * 0x44: MOVZ X17, 0xdef0        //wirte def0 LSL0  into x17 
         * 0x48: ORR X9, X15, X14        //puts 0x1234567800000000 into x9 
         * 0x4c: ORR X9, X9, X16         //puts 0x123456789abc0000 into x9 
         * 0x50: ORR X9, X9, X17         //puts 0x123456789abcdef0 into x9 
         * 0x54: STUR X9, [X20, 0x28]    //store x9 into memory location 0x28
         * 0x58: LDUR X10, [X20, 0x28]   //load 0x123456789abcdef0 into X10
         */ 
         
         64'h038: Data = {9'b110100101,2'b11,16'h1234,5'd14};
         64'h03c: Data = {9'b110100101,2'b10,16'h5678,5'd15};
         64'h040: Data = {9'b110100101,2'b01,16'h9abc,5'd16};
         64'h044: Data = {9'b110100101,2'b00,16'hdef0,5'd17};
         64'h048: Data = {11'b10101010000,5'd14,6'd0,5'd15,5'd9};
         64'h04c: Data = {11'b10101010000,5'd16,6'd0,5'd9,5'd9};
         64'h050: Data = {11'b10101010000,5'd17,6'd0,5'd9,5'd9}; 
         64'h054: Data = {11'b11111000000,9'h28,2'b00,5'd20,5'd9};
         64'h058: Data = {11'b11111000010,9'h28,2'b00,5'd20,5'd10};
          
          
        default: Data = 32'hXXXXXXXX;
        endcase
    end
endmodule

Processor.v
`timescale 1ns / 1ps
module singlecycle(
    input resetl,
    input [63:0] startpc,
    output reg [63:0] currentpc,
    output [63:0] dmemout,
    input CLK
);

    // Next PC connections
    wire [63:0] nextpc;       // The next PC, to be updated on clock cycle

    // Instruction Memory connections
    wire [31:0] instruction;  // The current instruction

    // Parts of instruction
  	wire [4:0] rd;            // The destination register
    wire [4:0] rm;            // Operand 1
  	wire [4:0] rn;    		  // Oprrderand 2
    wire [10:0] opcode;
  	wire [25:0] immediate;

    // Control wires
    wire reg2loc;
    wire alusrc;
    wire mem2reg;
    wire regwrite;
    wire memread;
    wire memwrite;
    wire branch;
    wire uncond_branch;
    wire [3:0] aluctrl;
  	wire [2:0] signop;

    // Register file connections
    wire [63:0] regoutA;     // Output A
    wire [63:0] regoutB;     // Output B

    // ALU connections
  	wire [63:0] muxW;
  	wire [63:0] muxB;
    wire [63:0] aluout;
    wire zero;

    // Immediate generator connections
    wire [63:0] extimm;

    // PC update logic
  	always @(negedge CLK)
    	begin
        	if (resetl)
           		currentpc <= nextpc;
        	else
           		currentpc <= startpc;	       
    	end

    InstructionMemory Instruction(
        .Data(instruction),
        .Address(currentpc)
    );
  

    control control(
        .reg2loc(reg2loc),
        .alusrc(alusrc),
        .mem2reg(mem2reg),
        .regwrite(regwrite),
        .memread(memread),
        .memwrite(memwrite),
        .branch(branch),
        .uncond_branch(uncond_branch),
        .aluop(aluctrl),
        .signop(signop),
        .opcode(opcode)
    );
    
    
    /*
    * Connect the remaining datapath elements below.
    * Do not forget any additional multiplexers that may be required.
    */
  
    // Parts of instruction
    assign rd = instruction[4:0];
    assign rm = instruction[9:5];
  	assign #2 rn = reg2loc ? instruction[4:0] : instruction[20:16];
    assign opcode = instruction[31:21];
  	assign immediate = instruction[25:0];  

  	RegisterFile REG(
      .BusA(regoutA),
		  .BusB(regoutB),
      .BusW(muxW),
		  .RA(rm),
		  .RB(rn),
		  .RW(rd),
      .RegWr(regwrite),
		  .Clk(CLK)
    );
  
    SignExtender ImmGen(
      .Imm64(extimm),
      .Imm26(immediate),
      .Ctrl(signop)
    );
 	
  	assign #2 muxB = alusrc ? extimm : regoutB;
  	ALU alu(
    	.BusA(regoutA),
      .BusB( muxB),
    	.BusW(aluout),
    	.Zero(zero),
    	.ALUCtrl(aluctrl)
    );

    DataMemory DM(
        .ReadData(dmemout),
      	.Address(aluout),
      	.WriteData(regoutB),
        .MemoryRead(memread),
        .MemoryWrite(memwrite),
        .Clock(CLK)
	);
    
  	assign #2 muxW = mem2reg ? dmemout : aluout;

  	NextPCLogic NextPCLogic(
        .NextPC(nextpc),
        .CurrentPC(currentpc),
        .SignExtImm64(extimm),
        .Branch(branch),
        .ALUZero(zero),
        .Uncondbranch(uncond_branch)
	);
  
  
endmodule

ProcessorTest.v
`timescale 1ns / 1ps

`define STRLEN 32
`define HalfClockPeriod 60
`define ClockPeriod `HalfClockPeriod * 2

module SingleCycleProcTest_v;

    initial
    begin
        $dumpfile("singlecycle.vcd");
        $dumpvars;
    end

    // These tasks are used to check if a given test has passed and
    // confirm that all tests passed.
    task passTest;
        input [63:0] actualOut, expectedOut;
        input [`STRLEN*8:0] testType;
        inout [7:0] 	  passed;

        if(actualOut == expectedOut) begin $display ("%s passed", testType); passed = passed + 1; end
        else $display ("%s failed: 0x%x should be 0x%x", testType, actualOut, expectedOut);
    endtask

    task allPassed;
        input [7:0] passed;
        input [7:0] numTests;

        if(passed == numTests) $display ("All tests passed");
        else $display("Some tests failed: %d of %d passed", passed, numTests);
    endtask

    // Inputs
    reg        CLK;
    reg        Reset_L;
    reg [63:0] startPC;
    reg [7:0]  passed;
    reg [15:0] watchdog;

    // Outputs
    wire [63:0] dMemOut;
    wire [63:0] currentPC;

    // Instantiate the Unit Under Test (UUT)
    singlecycle uut (
        .CLK(CLK),
        .resetl(Reset_L),
        .startpc(startPC),
        .currentpc(currentPC),
        .dmemout(dMemOut)
    );

    initial begin
        // Initialize Inputs
        Reset_L = 1;
        startPC = 0;
        passed = 0;

        // Initialize Watchdog timer
        watchdog = 0;

        // Wait for global reset
        #(1 * `ClockPeriod);

        // Program 1
        #1
        Reset_L = 0; startPC = 0;
        #(1 * `ClockPeriod);
        Reset_L = 1;

        // ***********************************************************
        // This while loop will continue cycling the processor until the
        // PC reaches the final instruction in the first test.  If the
        // program forms an infinite loop, never reaching the end, the
        // watchdog timer will kick in and kill simulation after 64K
        // cycles.
        // ***********************************************************
        while (currentPC < 64'h34)
        begin
           #(1 * `ClockPeriod);
          $display("CurrentPC:%h",currentPC);
        end
        #(1 * `ClockPeriod);// One more cycle to load the pass code from the DataMemory.
        passTest(dMemOut, 64'hF, "Results of Program 1", passed);

      // ***********************************************************
      while (currentPC < 64'h58 )
        begin
           #(1 * `ClockPeriod);
           $display("CurrentPC:%h",currentPC);
        end
        #(1 * `ClockPeriod);// One more cycle to load the pass code from the DataMemory.
      passTest(dMemOut, 64'h123456789abcdef0, "Results of Program 2", passed);
      // ***********************************************************

        // Done
        allPassed(passed, 2);   // Be sure to change the one to match
                                // the number of tests you add.
        $finish;
    end

    initial begin
        CLK = 0;
    end

    // The following is correct if clock starts at LOW level at StartTime //
    always begin
        #`HalfClockPeriod CLK = ~CLK;
        #`HalfClockPeriod CLK = ~CLK;
        watchdog = watchdog +1;
    end

    // Kill the simulation if the watchdog hits 64K cycles
    always @*
        if (watchdog == 16'hFF)
        begin
            $display("Watchdog Timer Expired.");
            $finish;
        end


endmodule

singlecycle.vcd
$date
	Thu Dec  3 20:47:17 2020
$end
$version
	Icarus Verilog
$end
$timescale
	1ps
$end
$scope module SingleCycleProcTest_v $end
$var wire 64 ! dMemOut [63:0] $end
$var wire 64 " currentPC [63:0] $end
$var reg 1 # CLK $end
$var reg 1 $ Reset_L $end
$var reg 8 % passed [7:0] $end
$var reg 64 & startPC [63:0] $end
$var reg 16 ' watchdog [15:0] $end
$scope module uut $end
$var wire 1 # CLK $end
$var wire 1 $ resetl $end
$var wire 64 ( startpc [63:0] $end
$var wire 1 ) zero $end
$var wire 1 * uncond_branch $end
$var wire 3 + signop [2:0] $end
$var wire 5 , rn [4:0] $end
$var wire 5 - rm [4:0] $end
$var wire 1 . regwrite $end
$var wire 64 / regoutB [63:0] $end
$var wire 64 0 regoutA [63:0] $end
$var wire 1 1 reg2loc $end
$var wire 5 2 rd [4:0] $end
$var wire 11 3 opcode [10:0] $end
$var wire 64 4 nextpc [63:0] $end
$var wire 64 5 muxW [63:0] $end
$var wire 64 6 muxB [63:0] $end
$var wire 1 7 memwrite $end
$var wire 1 8 memread $end
$var wire 1 9 mem2reg $end
$var wire 32 : instruction [31:0] $end
$var wire 26 ; immediate [25:0] $end
$var wire 64 < extimm [63:0] $end
$var wire 64 = dmemout [63:0] $end
$var wire 1 > branch $end
$var wire 1 ? alusrc $end
$var wire 64 @ aluout [63:0] $end
$var wire 4 A aluctrl [3:0] $end
$var reg 64 B currentpc [63:0] $end
$scope module DM $end
$var wire 1 # Clock $end
$var wire 64 C WriteData [63:0] $end
$var wire 1 7 MemoryWrite $end
$var wire 1 8 MemoryRead $end
$var wire 64 D Address [63:0] $end
$var reg 64 E ReadData [63:0] $end
$scope task initset $end
$var reg 64 F addr [63:0] $end
$var reg 64 G data [63:0] $end
$upscope $end
$upscope $end
$scope module ImmGen $end
$var wire 26 H Imm26 [25:0] $end
$var wire 64 I Imm64 [63:0] $end
$var wire 3 J Ctrl [2:0] $end
$var reg 64 K Imm64Reg [63:0] $end
$upscope $end
$scope module Instruction $end
$var wire 64 L Address [63:0] $end
$var reg 32 M Data [31:0] $end
$upscope $end
$scope module NextPCLogic $end
$var wire 64 N CurrentPC [63:0] $end
$var wire 64 O SignExtImm64 [63:0] $end
$var wire 1 * Uncondbranch $end
$var wire 1 > Branch $end
$var wire 1 ) ALUZero $end
$var reg 64 P NextPC [63:0] $end
$upscope $end
$scope module REG $end
$var wire 64 Q BusW [63:0] $end
$var wire 1 # Clk $end
$var wire 5 R RA [4:0] $end
$var wire 5 S RB [4:0] $end
$var wire 5 T RW [4:0] $end
$var wire 1 . RegWr $end
$var wire 64 U BusB [63:0] $end
$var wire 64 V BusA [63:0] $end
$upscope $end
$scope module alu $end
$var wire 64 W BusA [63:0] $end
$var wire 64 X BusB [63:0] $end
$var wire 1 ) Zero $end
$var wire 4 Y ALUCtrl [3:0] $end
$var reg 64 Z BusW [63:0] $end
$upscope $end
$scope module control $end
$var wire 11 [ opcode [10:0] $end
$var reg 4 \ aluop [3:0] $end
$var reg 1 ? alusrc $end
$var reg 1 > branch $end
$var reg 1 9 mem2reg $end
$var reg 1 8 memread $end
$var reg 1 7 memwrite $end
$var reg 1 1 reg2loc $end
$var reg 1 . regwrite $end
$var reg 3 ] signop [2:0] $end
$var reg 1 * uncond_branch $end
$upscope $end
$upscope $end
$scope task allPassed $end
$var reg 8 ^ numTests [7:0] $end
$var reg 8 _ passed [7:0] $end
$upscope $end
$scope task passTest $end
$var reg 64 ` actualOut [63:0] $end
$var reg 64 a expectedOut [63:0] $end
$var reg 8 b passed [7:0] $end
$var reg 257 c testType [256:0] $end
$upscope $end
$upscope $end
$enddefinitions $end
#0
$dumpvars
bx c
bx b
bx a
bx `
bx _
bx ^
bx ]
bx \
bx [
bx Z
bx Y
bx X
bx W
bx V
bx U
bx T
bx S
bx R
bx Q
bx P
bx O
bx N
bx M
bx L
bx K
bx J
bx I
bx H
b0 G
b100000 F
bx E
bx D
bx C
bx B
bx A
bx @
x?
x>
bx =
bx <
bx ;
bx :
x9
x8
x7
bx 6
bx 5
bx 4
bx 3
bx 2
x1
bx 0
bx /
x.
bx -
bx ,
bx +
x*
x)
b0 (
b0 '
b0 &
b0 %
1$
0#
bx "
bx !
$end
#60000
1#
#120000
b1 '
0#
#121000
0$
#180000
1#
#240000
b1 A
b1 Y
b1 \
0*
0>
07
08
1.
09
0?
01
b1111100000011111 <
b1111100000011111 I
b1111100000011111 K
b1111100000011111 O
b10000111110000001111110100 ;
b10000111110000001111110100 H
b10101010000 3
b10101010000 [
b11111 -
b11111 R
b10100 2
b10100 T
b10101010000111110000001111110100 :
b10101010000111110000001111110100 M
b0 "
b0 B
b0 L
b0 N
b10 '
0#
#241000
1$
#242000
b11111 ,
b11111 S
b0 0
b0 V
b0 W
b100 4
b100 P
#244000
b0 /
b0 C
b0 U
#246000
b0 6
b0 X
#266000
b0 @
b0 D
b0 Z
#267000
1)
#268000
b0 5
b0 Q
#300000
1#
#360000
b1 +
b1 J
b1 ]
b10 A
b10 Y
b10 \
18
19
1?
x1
b0 <
b0 I
b0 K
b0 O
b10000000000001010001001 ;
b10000000000001010001001 H
b11111000010 3
b11111000010 [
b10100 -
b10100 R
b1001 2
b1001 T
b11111000010000000000001010001001 :
b11111000010000000000001010001001 M
b100 "
b100 B
b100 L
b100 N
b11 '
0#
#362000
bx 5
bx Q
b0x00x ,
b0x00x S
bx 0
bx V
bx W
b1000 4
b1000 P
#364000
bx /
bx C
bx U
#365000
b0 0
b0 V
b0 W
#382000
bx @
bx D
bx Z
#383000
x)
#385000
b0 @
b0 D
b0 Z
#386000
1)
#420000
1#
#440000
b1 !
b1 =
b1 E
#442000
b1 5
b1 Q
#480000
b1000 <
b1000 I
b1000 K
b1000 O
b10000001000001010001010 ;
b10000001000001010001010 H
b1010 2
b1010 T
b11111000010000001000001010001010 :
b11111000010000001000001010001010 M
b1000 "
b1000 B
b1000 L
b1000 N
b100 '
0#
#482000
b1000 6
b1000 X
b0x0x0 ,
b0x0x0 S
b1100 4
b1100 P
#502000
b1000 @
b1000 D
b1000 Z
#503000
0)
#540000
1#
#560000
b1010 !
b1010 =
b1010 E
#562000
b1010 5
b1010 Q
#600000
b10000 <
b10000 I
b10000 K
b10000 O
b10000010000001010001011 ;
b10000010000001010001011 H
b1011 2
b1011 T
b11111000010000010000001010001011 :
b11111000010000010000001010001011 M
b1100 "
b1100 B
b1100 L
b1100 N
b101 '
0#
#602000
b10000 6
b10000 X
b0x0x1 ,
b0x0x1 S
b10000 4
b10000 P
#622000
b10000 @
b10000 D
b10000 Z
#660000
1#
#680000
b101 !
b101 =
b101 E
#682000
b101 5
b101 Q
#720000
b11000 <
b11000 I
b11000 K
b11000 O
b10000011000001010001100 ;
b10000011000001010001100 H
b1100 2
b1100 T
b11111000010000011000001010001100 :
b11111000010000011000001010001100 M
b10000 "
b10000 B
b10000 L
b10000 N
b110 '
0#
#722000
b11000 6
b11000 X
b0xx0x ,
b0xx0x S
b10100 4
b10100 P
#742000
b11000 @
b11000 D
b11000 Z
#780000
1#
#800000
b111111111011111010100111110111101010110110111110111011111111 !
b111111111011111010100111110111101010110110111110111011111111 =
b111111111011111010100111110111101010110110111110111011111111 E
#802000
b111111111011111010100111110111101010110110111110111011111111 5
b111111111011111010100111110111101010110110111110111011111111 Q
#840000
b100000 <
b100000 I
b100000 K
b100000 O
b10000100000001010001101 ;
b10000100000001010001101 H
b1101 2
b1101 T
b11111000010000100000001010001101 :
b11111000010000100000001010001101 M
b10100 "
b10100 B
b10100 L
b10100 N
b111 '
0#
#842000
b100000 6
b100000 X
b0xxxx ,
b0xxxx S
b11000 4
b11000 P
#862000
b100000 @
b100000 D
b100000 Z
#900000
1#
#920000
b0 !
b0 =
b0 E
#922000
b0 5
b0 Q
#960000
bx +
bx J
bx ]
b1 A
b1 Y
b1 \
08
09
0?
01
b101100000001010 <
b101100000001010 I
b101100000001010 K
b101100000001010 O
b10000010110000000101001010 ;
b10000010110000000101001010 H
b10101010000 3
b10101010000 [
b1010 -
b1010 R
b1010 2
b1010 T
b10101010000010110000000101001010 :
b10101010000010110000000101001010 M
b11000 "
b11000 B
b11000 L
b11000 N
b1000 '
0#
#962000
b100000 5
b100000 Q
bx 6
bx X
b1011 ,
b1011 S
b1010 0
b1010 V
b1010 W
b11100 4
b11100 P
#964000
b101 /
b101 C
b101 U
#966000
b101 6
b101 X
#982000
bx1x1x @
bx1x1x D
bx1x1x Z
#984000
bx1x1x 5
bx1x1x Q
#986000
b1111 @
b1111 D
b1111 Z
#988000
b1111 5
b1111 Q
#1020000
1#
#1080000
b0 A
b0 Y
b0 \
b101000000001100 <
b101000000001100 I
b101000000001100 K
b101000000001100 O
b10000010100000000110001100 ;
b10000010100000000110001100 H
b10001010000 3
b10001010000 [
b1100 -
b1100 R
b1100 2
b1100 T
b10001010000010100000000110001100 :
b10001010000010100000000110001100 M
b11100 "
b11100 B
b11100 L
b11100 N
b1001 '
0#
#1082000
b1010 ,
b1010 S
b111111111011111010100111110111101010110110111110111011111111 0
b111111111011111010100111110111101010110110111110111011111111 V
b111111111011111010100111110111101010110110111110111011111111 W
b100000 4
b100000 P
#1085000
b1111 /
b1111 C
b1111 U
#1087000
b1111 6
b1111 X
#1100000
b0 @
b0 D
b0 Z
#1101000
1)
#1102000
b101 @
b101 D
b101 Z
b0 5
b0 Q
#1103000
0)
#1104000
b101 5
b101 Q
#1107000
b1111 @
b1111 D
b1111 Z
#1109000
b1111 5
b1111 Q
#1140000
1#
#1200000
b11 +
b11 J
b11 ]
b111 A
b111 Y
b111 \
x*
1>
0.
x9
11
b100 <
b100 I
b100 K
b100 O
b10001100 ;
b10001100 H
b10110100000 3
b10110100000 [
b100 -
b100 R
b10110100000000000000000010001100 :
b10110100000000000000000010001100 M
b100000 "
b100000 B
b100000 L
b100000 N
b1010 '
0#
#1202000
b0xxxx 5
b0xxxx Q
b1100 ,
b1100 S
bx 0
bx V
bx W
b100100 4
b100100 P
#1260000
1#
